pds/__init__.py
pds/registrysweepers/VERSION.txt
pds/registrysweepers/__init__.py
pds/registrysweepers/ancestry/__init__.py
pds/registrysweepers/ancestry/ancestryrecord.py
pds/registrysweepers/ancestry/generation.py
pds/registrysweepers/ancestry/queries.py
pds/registrysweepers/ancestry/runtimeconstants.py
pds/registrysweepers/ancestry/typedefs.py
pds/registrysweepers/ancestry/utils.py
pds/registrysweepers/ancestry/versioning.py
pds/registrysweepers/legacy_registry_sync/__init__.py
pds/registrysweepers/legacy_registry_sync/legacy_registry_sync.py
pds/registrysweepers/legacy_registry_sync/opensearch_loaded_product.py
pds/registrysweepers/legacy_registry_sync/solr_doc_export_to_opensearch.py
pds/registrysweepers/provenance/__init__.py
pds/registrysweepers/provenance/constants.py
pds/registrysweepers/provenance/provenancerecord.py
pds/registrysweepers/provenance/versioning.py
pds/registrysweepers/repairkit/__init__.py
pds/registrysweepers/repairkit/allarrays.py
pds/registrysweepers/repairkit/versioning.py
pds/registrysweepers/utils/__init__.py
pds/registrysweepers/utils/majorminorversion.py
pds/registrysweepers/utils/misc.py
pds/registrysweepers/utils/db/__init__.py
pds/registrysweepers/utils/db/client.py
pds/registrysweepers/utils/db/indexing.py
pds/registrysweepers/utils/db/update.py
pds/registrysweepers/utils/productidentifiers/__init__.py
pds/registrysweepers/utils/productidentifiers/factory.py
pds/registrysweepers/utils/productidentifiers/pdslid.py
pds/registrysweepers/utils/productidentifiers/pdslidvid.py
pds/registrysweepers/utils/productidentifiers/pdsproductidentifier.py
pds/registrysweepers/utils/productidentifiers/pdsvid.py
pds.registry_moppers-3.6.0.dist-info/LICENSE.md
pds.registry_moppers-3.6.0.dist-info/METADATA
pds.registry_moppers-3.6.0.dist-info/NOTICE.txt
pds.registry_moppers-3.6.0.dist-info/WHEEL
pds.registry_moppers-3.6.0.dist-info/top_level.txt
pds.registry_moppers-3.6.0.dist-info/zip-safe
pds.registry_moppers-3.6.0.dist-info/RECORD
