Metadata-Version: 2.1
Name: pds.registry-moppers
Version: 3.6.0
Summary: Ignore this package
Home-page: https://github.com/nasa-pds-engineering-node/registry-moppers
Download-URL: https://github.com/nasa-pds-engineering-node/registry-moppers/releases/
Author: PDS
Author-email: pds_operator@jpl.nasa.gov
License: apache-2.0
Keywords: pds,planetary data,registry
Classifier: Programming Language :: Python :: 3
Classifier: Programming Language :: Python :: 3.9
Classifier: License :: OSI Approved :: Apache Software License
Classifier: Operating System :: OS Independent
Requires-Python: >=3.9
License-File: LICENSE.md
License-File: NOTICE.txt
Requires-Dist: opensearch-py ~=2.3.1
Requires-Dist: requests ~=2.28
Requires-Dist: retry ~=0.9.2
Requires-Dist: psutil ~=5.9.7
Requires-Dist: pds.solr-to-es ==0.3.0
Provides-Extra: dev
Requires-Dist: alabaster <=0.7.13 ; extra == 'dev'
Requires-Dist: black ~=23.7.0 ; extra == 'dev'
Requires-Dist: flake8 ~=6.1.0 ; extra == 'dev'
Requires-Dist: flake8-bugbear ~=23.7.10 ; extra == 'dev'
Requires-Dist: flake8-docstrings ~=1.7.0 ; extra == 'dev'
Requires-Dist: pep8-naming ~=0.13.3 ; extra == 'dev'
Requires-Dist: mypy ~=1.5.1 ; extra == 'dev'
Requires-Dist: pydocstyle ~=6.3.0 ; extra == 'dev'
Requires-Dist: coverage ~=7.3.0 ; extra == 'dev'
Requires-Dist: pytest ~=7.4.0 ; extra == 'dev'
Requires-Dist: pytest-cov ~=4.1.0 ; extra == 'dev'
Requires-Dist: pytest-watch ~=4.2.0 ; extra == 'dev'
Requires-Dist: pytest-xdist ~=3.3.1 ; extra == 'dev'
Requires-Dist: pre-commit ~=3.3.3 ; extra == 'dev'
Requires-Dist: sphinx ~=3.2.1 ; extra == 'dev'
Requires-Dist: sphinx-rtd-theme ~=0.5.0 ; extra == 'dev'
Requires-Dist: sphinxcontrib-applehelp ==1.0.4 ; extra == 'dev'
Requires-Dist: sphinxcontrib-devhelp ==1.0.2 ; extra == 'dev'
Requires-Dist: sphinxcontrib-htmlhelp ==2.0.1 ; extra == 'dev'
Requires-Dist: sphinxcontrib-jsmath ==1.0.1 ; extra == 'dev'
Requires-Dist: sphinxcontrib-qthelp ==1.0.3 ; extra == 'dev'
Requires-Dist: sphinxcontrib-serializinghtml ==1.1.5 ; extra == 'dev'
Requires-Dist: tox ~=4.11.0 ; extra == 'dev'
Requires-Dist: types-psutil ~=5.9.5 ; extra == 'dev'
Requires-Dist: types-requests ~=2.28 ; extra == 'dev'
Requires-Dist: types-retry ~=0.9.9.4 ; extra == 'dev'
Requires-Dist: types-setuptools ~=68.1.0.0 ; extra == 'dev'
Requires-Dist: Jinja2 <3.1 ; extra == 'dev'
